lmdb_embeddings/__init__.py
lmdb_embeddings/exceptions.py
lmdb_embeddings/reader.py
lmdb_embeddings/serializers.py
lmdb_embeddings/writer.py
lmdb_embeddings/tests/__init__.py
lmdb_embeddings/tests/test_embeddings.py
lmdb_embeddings-0.4.0.dist-info/LICENSE
lmdb_embeddings-0.4.0.dist-info/METADATA
lmdb_embeddings-0.4.0.dist-info/WHEEL
lmdb_embeddings-0.4.0.dist-info/top_level.txt
lmdb_embeddings-0.4.0.dist-info/RECORD
