Metadata-Version: 2.1
Name: lmdb-embeddings
Version: 0.4.0
Summary: Fast querying of word embeddings using the LMDB "Lightning" Database.
Home-page: https://www.thoughtriver.com
Author: Dom Hudson
Author-email: dom.hudson@thoughtriver.com
License: GNU General Public License v3.0
Platform: UNKNOWN
Requires-Dist: lmdb
Requires-Dist: msgpack
Requires-Dist: msgpack-numpy
Requires-Dist: numpy
Provides-Extra: develop
Requires-Dist: flake8 ; extra == 'develop'
Requires-Dist: pytest ; extra == 'develop'
Requires-Dist: pytest-cov ; extra == 'develop'
